gen3_metadata/__init__.py
gen3_metadata/gen3_metadata_parser.py
gen3_metadata/logger.py
gen3_metadata-1.1.0.dist-info/LICENSE
gen3_metadata-1.1.0.dist-info/METADATA
gen3_metadata-1.1.0.dist-info/WHEEL
gen3_metadata-1.1.0.dist-info/RECORD
