Metadata-Version: 2.3
Name: gen3-metadata
Version: 1.1.0
Summary: User friendly tools for downloading and manipulating gen3 metadata
License: Apache 2.0
Author: JoshuaHarris391
Author-email: harjo391@gmail.com
Requires-Python: >=3.9
Classifier: License :: Other/Proprietary License
Classifier: Programming Language :: Python :: 3
Classifier: Programming Language :: Python :: 3.9
Classifier: Programming Language :: Python :: 3.10
Classifier: Programming Language :: Python :: 3.11
Classifier: Programming Language :: Python :: 3.12
Classifier: Programming Language :: Python :: 3.13
Requires-Dist: pandas (>=2.3.1,<3.0.0)
Requires-Dist: pyjwt (>=2.10.1)
Requires-Dist: pytest (>=8.4.1,<9.0.0)
Requires-Dist: requests (>=2.32.4,<3.0.0)
Requires-Dist: setuptools (>=56.0.0)
